Traffic_Light_Controller.v
`timescale 1ns / 1ps

module Traffic_Light_Controller(
    input clk,  // Clock input for synchronization
    input rst,  // Reset signal to reset the system
    output reg [2:0] light_M1,  // Output for main road 1 traffic light
    output reg [2:0] light_S,   // Output for side road traffic light
    output reg [2:0] light_MT,  // Output for main road turning lane light
    output reg [2:0] light_M2   // Output for main road 2 traffic light
);

// State definitions for the finite state machine (FSM)
parameter S1 = 0, S2 = 1, S3 = 2, S4 = 3, S5 = 4, S6 = 5;

// Time intervals for each state in seconds (as counters)
parameter sec7 = 7, sec5 = 5, sec2 = 2, sec3 = 3;

// Variables for counting clock cycles and storing current state
reg [3:0] count;  // Counter to control how long the lights stay in a particular state
reg [2:0] ps;     // Current state (ps: present state)

// FSM (Finite State Machine) for controlling traffic lights
always @(posedge clk or posedge rst) begin
    if (rst == 1) begin
        ps <= S1;   // On reset, go to state S1
        count <= 0; // Reset the counter
    end
    else begin
        // State transition logic based on current state and counter
        case(ps)
            S1: if (count < sec7) begin
                    ps <= S1;        // Stay in state S1 for sec7 seconds
                    count <= count + 1;
                end
                else begin
                    ps <= S2;        // Move to state S2 after sec7 seconds
                    count <= 0;      // Reset counter
                end
            S2: if (count < sec2) begin
                    ps <= S2;        // Stay in state S2 for sec2 seconds
                    count <= count + 1;
                end
                else begin
                    ps <= S3;        // Move to state S3 after sec2 seconds
                    count <= 0;
                end
            S3: if (count < sec5) begin
                    ps <= S3;        // Stay in state S3 for sec5 seconds
                    count <= count + 1;
                end
                else begin
                    ps <= S4;        // Move to state S4 after sec5 seconds
                    count <= 0;
                end
            S4: if (count < sec2) begin
                    ps <= S4;        // Stay in state S4 for sec2 seconds
                    count <= count + 1;
                end
                else begin
                    ps <= S5;        // Move to state S5 after sec2 seconds
                    count <= 0;
                end
            S5: if (count < sec3) begin
                    ps <= S5;        // Stay in state S5 for sec3 seconds
                    count <= count + 1;
                end
                else begin
                    ps <= S6;        // Move to state S6 after sec3 seconds
                    count <= 0;
                end
            S6: if (count < sec2) begin
                    ps <= S6;        // Stay in state S6 for sec2 seconds
                    count <= count + 1;
                end
                else begin
                    ps <= S1;        // Move to state S1 after sec2 seconds (cycle restarts)
                    count <= 0;
                end
            default: ps <= S1;        // Default to state S1 if any unknown state occurs
        endcase
    end
end

// Output logic to control the traffic lights based on the current state
always @(ps) begin
    case (ps)
        S1: begin
            light_M1 <= 3'b001;  // Green light for main road 1
            light_M2 <= 3'b001;  // Green light for main road 2
            light_MT <= 3'b100;  // Red light for main road turn
            light_S  <= 3'b100;  // Red light for side road
        end
        S2: begin
            light_M1 <= 3'b001;  // Green light for main road 1
            light_M2 <= 3'b010;  // Yellow light for main road 2
            light_MT <= 3'b100;  // Red light for main road turn
            light_S  <= 3'b100;  // Red light for side road
        end
        S3: begin
            light_M1 <= 3'b001;  // Green light for main road 1
            light_M2 <= 3'b100;  // Red light for main road 2
            light_MT <= 3'b001;  // Green light for main road turn
            light_S  <= 3'b100;  // Red light for side road
        end
        S4: begin
            light_M1 <= 3'b010;  // Yellow light for main road 1
            light_M2 <= 3'b100;  // Red light for main road 2
            light_MT <= 3'b010;  // Yellow light for main road turn
            light_S  <= 3'b100;  // Red light for side road
        end
        S5: begin
            light_M1 <= 3'b100;  // Red light for main road 1
            light_M2 <= 3'b100;  // Red light for main road 2
            light_MT <= 3'b100;  // Red light for main road turn
            light_S  <= 3'b001;  // Green light for side road
        end
        S6: begin
            light_M1 <= 3'b100;  // Red light for main road 1
            light_M2 <= 3'b100;  // Red light for main road 2
            light_MT <= 3'b100;  // Red light for main road turn
            light_S  <= 3'b010;  // Yellow light for side road
        end
        default: begin
            light_M1 <= 3'b000;  // All lights off (default state)
            light_M2 <= 3'b000;
            light_MT <= 3'b000;
            light_S  <= 3'b000;
        end
    endcase
end

endmodule

Traffic Light Controller Vivado/project_1/Traffic_Light_Controller_TB.v
`timescale 1ns / 1ps
//////////////////////////////////////////////////////////////////////////////////
// Company: 
// Engineer: 
// 
// Create Date: 19.11.2024 17:22:56
// Design Name: 
// Module Name: Traffic_Light_Controller_TB
// Project Name: 
// Target Devices: 
// Tool Versions: 
// Description: 
// 
// Dependencies: 
// 
// Revision:
// Revision 0.01 - File Created
// Additional Comments:
// 
//////////////////////////////////////////////////////////////////////////////////

module Traffic_Light_Controller_TB;
    // Declare input signals (reg type) for the testbench
    reg clk, rst; 
    
    // Declare output signals (wire type) to monitor the state of the traffic lights
    wire [2:0] light_M1;   // Traffic light state for Main road 1
    wire [2:0] light_S;    // Traffic light state for Side road
    wire [2:0] light_MT;   // Traffic light state for Main road turning lane
    wire [2:0] light_M2;   // Traffic light state for Main road 2

    // Instantiate the Traffic Light Controller module (Device Under Test - DUT)
    Traffic_Light_Controller dut (
        .clk(clk), 
        .rst(rst), 
        .light_M1(light_M1), 
        .light_S(light_S), 
        .light_M2(light_M2), 
        .light_MT(light_MT)
    );

    // Initial block to generate clock signal
    initial begin
        clk = 1'b0;  // Initialize clock to 0
        
        // Dump file and variables for waveform analysis (for use with tools like GTKWave)
        $dumpfile("Traffic_Light_Controller_TB.vcd");  // Create dump file
        $dumpvars(0, Traffic_Light_Controller_TB);     // Dump all variables for waveform
        
        // Clock toggles every 0.5 seconds (500 million time units)
        forever #(1000000000 / 2) clk = ~clk;  // 1-second clock period
    end

    // Initial block to control reset and run the simulation
    initial begin
        rst = 0;           // Start with reset low (inactive)
        
        #1000000000;       // Wait for 1 second (1 billion time units)
        rst = 1;           // Activate reset (set high)
        
        #1000000000;       // Keep reset high for 1 second
        rst = 0;           // Deactivate reset (set low)
        
        // Run simulation for 10 seconds (10 billion time units)
        #(10000000000);    // Simulation time = 10 seconds
        
        $finish;           // End the simulation
    end

endmodule

Traffic Light Controller Vivado/project_1/project_1.sim/sim_1/behav/xsim/Traffic_Light_Controller_TB.vcd
$date
   Tue Nov 19 17:29:20 2024
$end

$version
  2024.1
  $dumpfile ("Traffic_Light_Controller_TB.vcd") 
$end

$timescale
  1ps
$end

$scope module Traffic_Light_Controller_TB $end
$var reg 1 ! clk $end
$var reg 1 " rst $end
$var wire 3 # light_M1 [2:0] $end
$var wire 3 $ light_S [2:0] $end
$var wire 3 % light_MT [2:0] $end
$var wire 3 & light_M2 [2:0] $end
$scope module dut $end
$var wire 1 ' clk $end
$var wire 1 ( rst $end
$var reg 3 ) light_M1 [2:0] $end
$var reg 3 * light_S [2:0] $end
$var reg 3 + light_MT [2:0] $end
$var reg 3 , light_M2 [2:0] $end
$var reg 4 - count [3:0] $end
$var reg 3 . ps [2:0] $end
$upscope $end
$upscope $end
$enddefinitions $end

#0
$dumpvars
0!
0"
bx #
bx $
bx %
bx &
0'
0(
bx )
bx *
bx +
bx ,
bx -
bx .
$end

#500000000000
1!
b1 #
b100 $
b100 %
b1 &
1'
b1 )
b100 *
b100 +
b1 ,
b0 .

#1000000000000
0!
1"
0'
1(
b0 -

#1500000000000
1!
1'

#2000000000000
0!
0"
0'
0(

#2500000000000
1!
1'
b1 -

#3000000000000
0!
0'

#3500000000000
1!
1'
b10 -

#4000000000000
0!
0'

#4500000000000
1!
1'
b11 -

#5000000000000
0!
0'

#5500000000000
1!
1'
b100 -

#6000000000000
0!
0'

#6500000000000
1!
1'
b101 -

#7000000000000
0!
0'

#7500000000000
1!
1'
b110 -

#8000000000000
0!
0'

#8500000000000
1!
1'
b111 -

#9000000000000
0!
0'

#9500000000000
1!
b10 &
1'
b10 ,
b0 -
b1 .

#10000000000000
0!
0'

#10500000000000
1!
1'
b1 -

#11000000000000
0!
0'

#11500000000000
1!
1'
b10 -

#12000000000000
0!
0'

#12500000000000
1!
b1 %
b100 &
1'
b1 +
b100 ,
b0 -
b10 .

